geocolor/__init__.py
geocolor/common.py
geocolor/geocolor.py
geocolor-0.0.2.dist-info/licenses/LICENSE
geocolor-0.0.2.dist-info/METADATA
geocolor-0.0.2.dist-info/WHEEL
geocolor-0.0.2.dist-info/entry_points.txt
geocolor-0.0.2.dist-info/top_level.txt
geocolor-0.0.2.dist-info/RECORD
