Metadata-Version: 2.4
Name: geocolor
Version: 0.0.2
Summary: A package for mapping colors
Author-email: BH Z <zbhgisrs@gmail.com>
License: MIT License
Project-URL: Homepage, https://github.com/zbhgis/geocolor
Keywords: geocolor
Classifier: Intended Audience :: Developers
Classifier: License :: OSI Approved :: MIT License
Classifier: Natural Language :: English
Classifier: Programming Language :: Python :: 3.8
Classifier: Programming Language :: Python :: 3.9
Classifier: Programming Language :: Python :: 3.10
Classifier: Programming Language :: Python :: 3.11
Classifier: Programming Language :: Python :: 3.12
Requires-Python: >=3.8
License-File: LICENSE
Requires-Dist: numpy
Provides-Extra: all
Requires-Dist: geocolor[extra]; extra == "all"
Provides-Extra: extra
Requires-Dist: pandas; extra == "extra"
Dynamic: license-file
